backup/__init__.py
backup/py.typed
backup/backup/__init__.py
backup/backup/backup.py
backup/backup/change_scanner.py
backup/backup/cache/__init__.py
backup/backup/cache/cache_scanner.py
backup/backup/cache/cache_syncer.py
backup/backup/cache/entry.py
backup/backup/cache/checkers/__init__.py
backup/backup/cache/checkers/detailed.py
backup/backup/cache/checkers/path.py
backup/cli/__init__.py
backup/cli/entry_point.py
backup/cli/mount.py
backup/context/__init__.py
backup/context/action.py
backup/context/config.py
backup/context/context.py
backup/context/options.py
backup/context/secrets_.py
backup/main/__init__.py
backup/main/main.py
backup/main/mount.py
backup/models/__init__.py
backup/models/backup_config.py
backup/models/change.py
backup/models/change_type.py
backup/models/changes.py
backup/models/path.py
backup/models/print_change.py
backup/models/print_structure.py
backup/storage/__init__.py
backup/storage/storage.py
backup/syncer/__init__.py
backup/syncer/cli_runner.py
backup/syncer/filters.py
backup/syncer/status.py
backup/syncer/sync_config.py
backup/syncer/sync_configs.py
backup/syncer/syncer.py
backup/utils/__init__.py
backup/utils/error_handling.py
backup/utils/exporter.py
backup/utils/itertools.py
backup/utils/output_generator.py
backup/utils/setup.py
backup/utils/parser/__init__.py
backup/utils/parser/config.py
backup/utils/parser/rules.py
backupmaster-2.0.3.dist-info/licenses/LICENSE
backupmaster-2.0.3.dist-info/METADATA
backupmaster-2.0.3.dist-info/WHEEL
backupmaster-2.0.3.dist-info/entry_points.txt
backupmaster-2.0.3.dist-info/top_level.txt
backupmaster-2.0.3.dist-info/RECORD
