Metadata-Version: 2.4
Name: backupmaster
Version: 2.0.3
Summary: Backup import files across entire disk
Author-email: Quinten Roets <qdr2104@columbia.edu>
License-Expression: MIT
Project-URL: Source Code, https://github.com/quintenroets/backup
Requires-Python: <3.14,>=3.10
License-File: LICENSE
Requires-Dist: beautifulsoup4<5,>=4.12.2
Requires-Dist: lxml<7,>=4.9.3
Requires-Dist: package-utils[context]<1,>=0.6.4
Requires-Dist: powercli<1,>=0.3.0
Requires-Dist: PyYAML<7,>=6.0.1
Requires-Dist: xattr<2,>=0.10.1
Provides-Extra: dev
Requires-Dist: dirhash<1,>=0.2.1; extra == "dev"
Requires-Dist: package-dev-tools<1,>=0.7.1; extra == "dev"
Requires-Dist: package-dev-utils<1,>=0.1.6; extra == "dev"
Requires-Dist: types-beautifulsoup4<5,>=4.12.0.20240106; extra == "dev"
Dynamic: license-file
